app/__init__.py
app/database.py
app/main.py
app/password_strength.py
CipherSmith-1.3.0.dist-info/LICENSE
CipherSmith-1.3.0.dist-info/METADATA
CipherSmith-1.3.0.dist-info/WHEEL
CipherSmith-1.3.0.dist-info/entry_points.txt
CipherSmith-1.3.0.dist-info/top_level.txt
CipherSmith-1.3.0.dist-info/RECORD
