Metadata-Version: 2.1
Name: CipherSmith
Version: 1.3.0
Summary: A powerful password generator with real-time strength analysis
Home-page: https://github.com/amulthantharate/CipherSmith
Author: Amul Thantharate
Author-email: amulthantharate@gmail.com
Classifier: Programming Language :: Python :: 3
Classifier: License :: OSI Approved :: MIT License
Classifier: Operating System :: OS Independent
Requires-Python: >=3.9
License-File: LICENSE
Requires-Dist: typer>=0.9.0
Requires-Dist: rich>=10.0.0
Requires-Dist: zxcvbn-python>=4.4.24
Requires-Dist: cryptography>=41.0.0
Requires-Dist: sqlalchemy>=2.0.0
Requires-Dist: click>=8.0.0
Requires-Dist: colorama>=0.4.4
